{"cameraMode":{"drawMode":0,"name":"Shaded","section":"Shading Mode"},"sceneLighting":false,"audioPlay":false,"sceneViewState":{"m_AlwaysRefresh":false,"showFog":true,"showSkybox":true,"showFlares":true,"showImageEffects":true,"showParticleSystems":true,"showVisualEffectGraphs":true,"m_FxEnabled":true},"in2DMode":false,"pivot":{"x":-3.861604690551758,"y":3.6613311767578127,"z":-10.31906509399414},"rotation":{"x":-0.3845849335193634,"y":-0.018347006291151048,"z":0.007626004051417112,"w":-0.9229719042778015},"size":2.517338275909424,"orthographic":false}