{"cameraMode":{"drawMode":0,"name":"Shaded","section":"Shading Mode"},"sceneLighting":false,"audioPlay":false,"sceneViewState":{"m_AlwaysRefresh":false,"showFog":true,"showSkybox":false,"showFlares":true,"showImageEffects":true,"showParticleSystems":true,"showVisualEffectGraphs":true,"m_FxEnabled":true},"in2DMode":false,"pivot":{"x":0.0,"y":-0.1324000060558319,"z":0.15480145812034608},"rotation":{"x":-0.2764696478843689,"y":-0.5188277959823608,"z":0.18918700516223908,"w":-0.787187397480011},"size":0.9050793051719666,"orthographic":false}